README.md
setup.py
train.py
well_data_1.xls
bert/__init__.py
bert/convert_tf_checkpoint_to_pytorch.py
bert/modeling.py
bert/tokenization.py
cupkb.egg-info/PKG-INFO
cupkb.egg-info/SOURCES.txt
cupkb.egg-info/dependency_links.txt
cupkb.egg-info/requires.txt
cupkb.egg-info/top_level.txt
sqlnet/__init__.py
sqlnet/dbengine.py
sqlova/__init__.py
sqlova/model/__init__.py
sqlova/model/nl2sql/__init__.py
sqlova/model/nl2sql/wikisql_models.py
sqlova/utils/__init__.py
sqlova/utils/utils.py
sqlova/utils/utils_wikisql.py
sqlova/utils/wikisql_formatter.py
wikisql/__init__.py
wikisql/annotate.py
wikisql/evaluate.py
wikisql/lib/__init__.py
wikisql/lib/common.py
wikisql/lib/dbengine.py
wikisql/lib/query.py
wikisql/lib/table.py