Metadata-Version: 1.0
Name: cupkb
Version: 1.0.4
Summary: text2sql
Home-page: UNKNOWN
Author: UNKNOWN
Author-email: UNKNOWN
License: UNKNOWN
Platform: UNKNOWN
